{"id":"export-file.js","dependencies":[{"name":"E:\\frontend\\AIC\\package.json","includedInParent":true,"mtime":1537414043694},{"name":"E:\\frontend\\AIC\\.babelrc","includedInParent":true,"mtime":1537091743065},{"name":"./handle-urlencode","loc":{"line":1,"column":28},"parent":"E:\\frontend\\AIC\\export-file.js","resolved":"E:\\frontend\\AIC\\handle-urlencode.js"}],"generated":{"js":"\"use strict\";\n\nObject.defineProperty(exports, \"__esModule\", {\n  value: true\n});\n\nvar _handleUrlencode = require(\"./handle-urlencode\");\n\nvar _handleUrlencode2 = _interopRequireDefault(_handleUrlencode);\n\nfunction _interopRequireDefault(obj) { return obj && obj.__esModule ? obj : { default: obj }; }\n\nvar exportFile = function exportFile(_ref) {\n  var _ref$url = _ref.url,\n      url = _ref$url === undefined ? \"\" : _ref$url,\n      _ref$data = _ref.data,\n      data = _ref$data === undefined ? {} : _ref$data;\n\n  window.open(url + \"?\" + (0, _handleUrlencode2.default)(data));\n};\nexports.default = exportFile;","map":{"mappings":[{"generated":{"line":7,"column":0},"source":"export-file.js","original":{"line":1,"column":0}},{"generated":{"line":13,"column":0},"source":"export-file.js","original":{"line":2,"column":0}},{"name":"exportFile","generated":{"line":13,"column":4},"source":"export-file.js","original":{"line":2,"column":4}},{"generated":{"line":13,"column":17},"source":"export-file.js","original":{"line":2,"column":17}},{"name":"exportFile","generated":{"line":13,"column":26},"source":"export-file.js","original":{"line":2,"column":4}},{"generated":{"line":13,"column":36},"source":"export-file.js","original":{"line":2,"column":17}},{"generated":{"line":13,"column":43},"source":"export-file.js","original":{"line":2,"column":46}},{"generated":{"line":14,"column":0},"source":"export-file.js","original":{"line":2,"column":46}},{"name":"url","generated":{"line":14,"column":22},"source":"export-file.js","original":{"line":2,"column":20}},{"generated":{"line":14,"column":25},"source":"export-file.js","original":{"line":2,"column":46}},{"generated":{"line":15,"column":0},"source":"export-file.js","original":{"line":2,"column":46}},{"name":"url","generated":{"line":15,"column":6},"source":"export-file.js","original":{"line":2,"column":20}},{"generated":{"line":15,"column":9},"source":"export-file.js","original":{"line":2,"column":46}},{"generated":{"line":15,"column":37},"source":"export-file.js","original":{"line":2,"column":26}},{"generated":{"line":15,"column":39},"source":"export-file.js","original":{"line":2,"column":46}},{"generated":{"line":16,"column":0},"source":"export-file.js","original":{"line":2,"column":46}},{"name":"data","generated":{"line":16,"column":23},"source":"export-file.js","original":{"line":2,"column":30}},{"generated":{"line":16,"column":27},"source":"export-file.js","original":{"line":2,"column":46}},{"generated":{"line":17,"column":0},"source":"export-file.js","original":{"line":2,"column":46}},{"name":"data","generated":{"line":17,"column":6},"source":"export-file.js","original":{"line":2,"column":30}},{"generated":{"line":17,"column":10},"source":"export-file.js","original":{"line":2,"column":46}},{"generated":{"line":17,"column":39},"source":"export-file.js","original":{"line":2,"column":37}},{"generated":{"line":17,"column":41},"source":"export-file.js","original":{"line":2,"column":46}},{"name":"window","generated":{"line":19,"column":0},"source":"export-file.js","original":{"line":3,"column":2}},{"name":"open","generated":{"line":19,"column":9},"source":"export-file.js","original":{"line":3,"column":9}},{"generated":{"line":19,"column":13},"source":"export-file.js","original":{"line":3,"column":2}},{"name":"url","generated":{"line":19,"column":14},"source":"export-file.js","original":{"line":3,"column":14}},{"generated":{"line":19,"column":20},"source":"export-file.js","original":{"line":3,"column":20}},{"generated":{"line":19,"column":23},"source":"export-file.js","original":{"line":3,"column":14}},{"generated":{"line":19,"column":26},"source":"export-file.js","original":{"line":3,"column":26}},{"name":"data","generated":{"line":19,"column":57},"source":"export-file.js","original":{"line":3,"column":42}},{"generated":{"line":19,"column":61},"source":"export-file.js","original":{"line":3,"column":26}},{"generated":{"line":19,"column":62},"source":"export-file.js","original":{"line":3,"column":2}},{"generated":{"line":20,"column":0},"source":"export-file.js","original":{"line":4,"column":1}},{"generated":{"line":20,"column":1},"source":"export-file.js","original":{"line":2,"column":0}},{"name":"exportFile","generated":{"line":21,"column":18},"source":"export-file.js","original":{"line":5,"column":15}}],"sources":{"export-file.js":"import handleUrlEncode from \"./handle-urlencode\";\r\nlet exportFile = ({ url = \"\", data = {} }) => {\r\n  window.open(url + \"?\" + handleUrlEncode(data));\r\n};\r\nexport default exportFile;\r\n"},"lineCount":null}},"hash":"34d941263b6d616b6ca596ba0f508cdd","cacheData":{"env":{}}}